LICENSE.txt
MANIFEST.in
README.md
setup.cfg
setup.py
djangorestfilemanager/__init__.py
djangorestfilemanager/admin.py
djangorestfilemanager/app_settings.py
djangorestfilemanager/apps.py
djangorestfilemanager/filters.py
djangorestfilemanager/models.py
djangorestfilemanager/permissions.py
djangorestfilemanager/serializers.py
djangorestfilemanager/settings.py
djangorestfilemanager/urls.py
djangorestfilemanager/views.py
djangorestfilemanager.egg-info/PKG-INFO
djangorestfilemanager.egg-info/SOURCES.txt
djangorestfilemanager.egg-info/dependency_links.txt
djangorestfilemanager.egg-info/requires.txt
djangorestfilemanager.egg-info/top_level.txt
djangorestfilemanager/locale/en/LC_MESSAGES/django.mo
djangorestfilemanager/locale/en/LC_MESSAGES/django.po
djangorestfilemanager/locale/es/LC_MESSAGES/django.mo
djangorestfilemanager/locale/es/LC_MESSAGES/django.po
djangorestfilemanager/migrations/0001_initial.py
djangorestfilemanager/migrations/0002_auto_20200302_0947.py
djangorestfilemanager/migrations/0003_auto_20200311_1022.py
djangorestfilemanager/migrations/0004_auto_20200318_1806.py
djangorestfilemanager/migrations/0005_auto_20200319_1235.py
djangorestfilemanager/migrations/0006_auto_20200429_1220.py
djangorestfilemanager/migrations/0007_alter_file_name.py
djangorestfilemanager/migrations/0008_alter_file_field.py
djangorestfilemanager/migrations/0009_auto_20210810_0945.py
djangorestfilemanager/migrations/0010_auto_alter_data.py
djangorestfilemanager/migrations/0011_alter_file_file.py
djangorestfilemanager/migrations/__init__.py
djangorestfilemanager/tests/__init__.py
djangorestfilemanager/tests/test_download_files.py
djangorestfilemanager/tests/test_upload_files.py