Metadata-Version: 2.1
Name: djangorestfilemanager
Version: 2.0.2
Summary: Django REST File Manager.
Home-page: https://gitlab.com/kas-factory/packages/django-rest-file-manager
Author: Avelino @ KF
Author-email: avelino@kasfactory.net
License: COPYRIGHT
Platform: UNKNOWN
License-File: LICENSE.txt
